{
  "db_name": "PostgreSQL",
  "query": "\n                delete from notification_message \n                where created_at < $1::timestamptz\n                returning *\n            ",
  "describe": {
    "columns": [
      {
        "ordinal": 0,
        "name": "id",
        "type_info": "Int8"
      },
      {
        "ordinal": 1,
        "name": "channel",
        "type_info": "Varchar"
      },
      {
        "ordinal": 2,
        "name": "subject",
        "type_info": "Varchar"
      },
      {
        "ordinal": 3,
        "name": "message",
        "type_info": "Varchar"
      },
      {
        "ordinal": 4,
        "name": "created_at",
        "type_info": "Timestamptz"
      },
      {
        "ordinal": 5,
        "name": "updated_at",
        "type_info": "Timestamptz"
      }
    ],
    "parameters": {
      "Left": [
        "Timestamptz"
      ]
    },
    "nullable": [
      false,
      false,
      false,
      false,
      false,
      false
    ]
  },
  "hash": "dbbbd8de9c3ac883418e9d2c7a54f9496ed871fe2f55de9933571b9f11e3e5c9"
}
